aimDIAS/DIAS.py
aimDIAS/__init__.py
aimDIAS/aimnet2ase.py
aimDIAS/samples.py
aimDIAS/utilities.py
aimDIAS/models/aimnet2_b973c_ens.jpt
aimDIAS/models/aimnet2_wb97m-d3_ens.jpt
build/lib/aimDIAS/DIAS.py
build/lib/aimDIAS/__init__.py
build/lib/aimDIAS/aimnet2ase.py
build/lib/aimDIAS/samples.py
build/lib/aimDIAS/utilities.py
aimDIAS-1.1.0.dist-info/LICENSE
aimDIAS-1.1.0.dist-info/METADATA
aimDIAS-1.1.0.dist-info/WHEEL
aimDIAS-1.1.0.dist-info/top_level.txt
aimDIAS-1.1.0.dist-info/RECORD
