Metadata-Version: 2.1
Name: aimDIAS
Version: 1.1.0
Summary: SUPER FAST D/I analysis with aimnet2
Home-page: https://github.com/kangmg/aimDIAS
Author: Kang mingi
Author-email: kangmg@korea.ac.kr
Keywords: chemistry,computational chemistry,machine learning
Classifier: Programming Language :: Python :: 3
Classifier: License :: OSI Approved :: MIT License
Classifier: Operating System :: OS Independent
Classifier: Topic :: Scientific/Engineering :: Chemistry
Requires-Python: >=3.10.0
License-File: LICENSE
Requires-Dist: matplotlib
Requires-Dist: numpy
Requires-Dist: requests
Requires-Dist: ase >=3.22.1
Requires-Dist: torch >=2.2.1
Requires-Dist: rdkit >=2023.09.6
Requires-Dist: py3Dmol >=2.1.0
